data_worker/__init__.py
data_worker/data_worker.py
data_worker/defined_wrappers.py
data_worker/mapper.py
data_worker/utils.py
data_worker/data/__init__.py
data_worker/data/api_meta_data.json
data_worker/wrappers/__init__.py
data_worker/wrappers/alpha_vantage_wrapper.py
data_worker/wrappers/quandl_wrapper.py
data_worker/wrappers/wrapper.py
data_worker-0.1.6.dist-info/LICENSE
data_worker-0.1.6.dist-info/METADATA
data_worker-0.1.6.dist-info/WHEEL
data_worker-0.1.6.dist-info/top_level.txt
data_worker-0.1.6.dist-info/RECORD
