Metadata-Version: 2.1
Name: data-worker
Version: 0.1.6
Summary: An API wrapper for all data sources used by Synechron's Data Science team
Home-page: https://gitlab.com/Kevin.OBrien/data_worker
Author: Kevin O'Brien
Author-email: Kevin.OBrien@Synechron.com
License: UNKNOWN
Platform: UNKNOWN
Classifier: Programming Language :: Python :: 3
Classifier: Operating System :: OS Independent
